rickroll/__init__.py
rickroll/functions.py
rickrollpy-1.0.0.dist-info/LICENSE
rickrollpy-1.0.0.dist-info/METADATA
rickrollpy-1.0.0.dist-info/WHEEL
rickrollpy-1.0.0.dist-info/top_level.txt
rickrollpy-1.0.0.dist-info/RECORD
