Metadata-Version: 2.1
Name: rickrollpy
Version: 1.0.0
Summary: Wanna rickroll people? Use this!
Home-page: UNKNOWN
Author: th3atom
Author-email: UNKNOWN
License: MIT
Platform: UNKNOWN
